[
  {
    "id": 1,
    "question": "문제1",
    "answers": [
      {
        "point": "10",
        "content": "답1"
      },
      {
        "point": "0",
        "content": "답2"
      }
    ]
  },
  {
    "id": 2,
    "question": "문제2",
    "answers": [
      {
        "point": "10",
        "content": "답1"
      },
      {
        "point": "0",
        "content": "답2"
      }
    ]
  },
  {
    "id": 3,
    "question": "문제3",
    "answers": [
      {
        "point": "10",
        "content": "답1"
      },
      {
        "point": "0",
        "content": "답2"
      }
    ]
  },
  {
    "id": 4,
    "question": "문제4",
    "answers": [
      {
        "point": "10",
        "content": "답1"
      },
      {
        "point": "0",
        "content": "답2"
      }
    ]
  },
  {
    "id": 5,
    "question": "문제5",
    "answers": [
      {
        "point": "10",
        "content": "답1"
      },
      {
        "point": "0",
        "content": "답2"
      }
    ]
  },
  {
    "id": 6,
    "question": "문제6",
    "answers": [
      {
        "point": "10",
        "content": "답1"
      },
      {
        "point": "0",
        "content": "답2"
      }
    ]
  },
  {
    "id": 7,
    "question": "문제7",
    "answers": [
      {
        "point": "10",
        "content": "답1"
      },
      {
        "point": "0",
        "content": "답2"
      }
    ]
  },
  {
    "id": 8,
    "question": "문제8",
    "answers": [
      {
        "point": "10",
        "content": "답1"
      },
      {
        "point": "0",
        "content": "답2"
      }
    ]
  },
  {
    "id": 9,
    "question": "문제9",
    "answers": [
      {
        "point": "10",
        "content": "답1"
      },
      {
        "point": "0",
        "content": "답2"
      }
    ]
  },
  {
    "id": 10,
    "question": "문제10",
    "answers": [
      {
        "point": "10",
        "content": "답1"
      },
      {
        "point": "0",
        "content": "답2"
      }
    ]
  }
]
